Workbook

Sheet Dashboard
A1: RIVERSTONE VALLEY (LQV) — FINANCIAL MODEL
A2: Phase 1: 5 cabins | Phase 2: 10 total | Phase 3: 30 total | Horizon: 2030 (Sonja's 60th)
A3: Generated 2026-07-06 by Erebus | Source: FINANCIAL_MODEL.md (Wes data 2026-06-30) + 4 working research docs
A4: Currency: EUR canonical | FX: 1 EUR = 1.07 USD = 8,025 PYG (BCP 2026-07-06 referencial)
A6: SCENARIO TOGGLE
A7: Selected scenario: | B7: GOOD (35% occupancy)
A8: Dashboard shows GOOD. For NEGATIVE (20%) or AVERAGE (25%), see Revenue + Sensitivity sheets.
A10: KEY 5-YEAR METRICS (GOOD SCENARIO)
A12: Metric | B12: Year 1 | C12: Year 2 | D12: Year 3 | E12: Year 4 | F12: Year 5
A13: Cabins available | B13: 5 | C13: 10 | D13: 30 | E13: 30 | F13: 30
A14: ADR (EUR/night) | B14: 220 | C14: 240 | D14: 260 | E14: 280 | F14: 300
A15: Occupancy % | B15: 0.25 | C15: 0.3 | D15: 0.35 | E15: 0.4 | F15: 0.4
A16: Cabin revenue (EUR) | B16: 100375 | C16: 262800 | D16: 996450 | E16: 1226400 | F16: 1314000
A17: F&B revenue (35% of cabin) | B17: =B16*0.35 | C17: =C16*0.35 | D17: =D16*0.35 | E17: =E16*0.35 | F17: =F16*0.35
A18: Other revenue (events/wellness, 10%) | B18: =B16*0.10 | C18: =C16*0.10 | D18: =D16*0.10 | E18: =E16*0.10 | F18: =F16*0.10
A19: TOTAL REVENUE | B19: =SUM(B16:B18) | C19: =SUM(C16:C18) | D19: =SUM(D16:D18) | E19: =SUM(E16:E18) | F19: =SUM(F16:F18)
A21: COSTS (PY social costs included)
A22: Staff (incl. 16.5% IPS + aguinaldo + vacaciones, 30% overhead) | B22: 70200 | C22: 105300 | D22: 315900 | E22: 315900 | F22: 315900
A23: Variable operating (F&B COGS 38% + OTA 5%) | B23: =B17*0.38 + B16*0.05 | C23: =C17*0.38 + C16*0.05 | D23: =D17*0.38 + D16*0.05 | E23: =E17*0.38 + E16*0.05 | F23: =F17*0.38 + F16*0.05
A24: Fixed operating (utilities, maintenance, marketing, insurance, 18% of revenue) | B24: =B19*0.18 | C24: =C19*0.18 | D24: =D19*0.18 | E24: =E19*0.18 | F24: =F19*0.18
A25: TOTAL COSTS | B25: =SUM(B22:B24) | C25: =SUM(C22:C24) | D25: =SUM(D22:D24) | E25: =SUM(E22:E24) | F25: =SUM(F22:F24)
A27: OPERATING PROFIT (EBIT) | B27: =B19-B25 | C27: =C19-C25 | D27: =D19-D25 | E27: =E19-E25 | F27: =F19-F25
A28: D&A on capex (straight-line 20yr) | B28: 275000 | C28: 540000 | D28: 835000 | E28: 835000 | F28: 835000
A29: EBT (Earnings Before Tax) | B29: =B27-B28 | C29: =C27-C28 | D29: =D27-D28 | E29: =E27-E28 | F29: =F27-F28
A31: TAXES (PY IRE 10% + NL Box 2 24.5% on dividends; see TaxProjection sheet for full 5-year side-by-side)
A32: For cash flow + the 4-BV vs IB vs 5-BV comparison, see sheets 7-8

Sheet Assumptions
A1: ASSUMPTIONS — all rates editable here, all sheets reference these
A3: FX RATES (BCP 2026-07-06 referencial)
A4: EUR/USD | B4: 1.07
A5: USD/PYG | B5: 7500
A6: EUR/PYG (derived) | B6: =B4*B5
A8: INFLATION (annual)
A9: EUR inflation (EU target ~2%) | B9: 0.02
A10: USD inflation (US ~2.5%) | B10: 0.025
A11: PYG inflation (PY ~4% historical) | B11: 0.04
A12: PY peso devaluation (PY 4-6% historical) | B12: 0.05
A14: TAX RATES (per LEGAL_RESEARCH_PACK_2026-07-06.md)
A15: PY IRE (Impuesto a la Renta Empresarial) | B15: 0.1
A16: PY IRP top bracket | B16: 0.1
A17: PY IVA standard | B17: 0.1
A18: PY IVA lodging | B18: 0.05
A19: PY tourism promotion | B19: 0.01
A20: PY IPS employer aporte | B20: 0.165
A21: PY aguinaldo (1/12 of annual) | B21: 0.0833
A22: PY vacaciones overhead (~12 d/yr) | B22: 0.05
A23: NL IB Box 2 (substantial interest, dividends) | B23: 0.245
A24: NL IB Box 2 high bracket | B24: 0.33
A25: NL dividend WHT to PY (treaty) | B25: 0.1
A26: NL BV > IB threshold | B26: 70000
A27: Effective double-tax rate (BV+Box2+IRE) | B27: 0.324
A29: SCENARIO PARAMETERS (3 scenarios per Wes FINANCIAL_MODEL.md)
A30: Scenario | B30: Occupancy | C30: Notes
A31: NEGATIVE | B31: 0.2 | C31: 20% occupancy, soft launch
A32: AVERAGE | B32: 0.25 | C32: 25% occupancy, slow ramp
A33: GOOD | B33: 0.35 | C33: 35% occupancy, established market
A34: VERY GOOD | B34: 0.45 | C34: added for sensitivity analysis

Sheet Capex
A1: CAPEX SUMMARY — Phase 1 (5-cabin baseline) + Phase 2-3 (10 → 30 cabins)
A2: Source: CAPEX_OPTIONS_2026-07-06.md (4-doc research pack) + FINANCIAL_MODEL.md
A4: PHASE 1 CAPEX (5 cabins + restaurant + pool)
A5: Block | B5: EUR | C5: Source/Note
A6: Land (62 ha, already owned) | B6: 0 | C6: excluded per FINANCIAL_MODEL.md
A7: Construction (5 cob cabins @ €54K) | B7: 270000 | C7: CAPEX_OPTIONS §B.1 Option A: cob + foundation + roof
A8: Restaurant + kitchen building (shell + equipment) | B8: 468000 | C8: CAPEX_OPTIONS §B.7 €68K equipment + €400K shell
A9: Wellness pool (Phase 1 plunge only) | B9: 35000 | C9: CAPEX_OPTIONS §A.1 baseline; full wellness deferred to Phase 2
A10: Roads + parking + fencing + signage | B10: 400000 | C10: FINANCIAL_MODEL.md + CAPEX_OPTIONS §E hidden capex
A11: Utilities (solar 8kW/cabin + quebrada+well + septic 5 systems) | B11: 129300 | C11: CAPEX_OPTIONS §B.4-B.6 corrected
A12: ANDE 3-phase grid connection + transformer | B12: 12000 | C12: CAPEX_OPTIONS §E.2
A13: Water + septic INAA permit | B13: 1800 | C13: F14, F15
A14: Municipality commercial + SENATUR + health permits | B14: 13000 | C14: CAPEX_OPTIONS §E.1-E.4
A15: MADES environmental impact study | B15: 4500 | C15: if >3 ha cleared
A16: F05 road upgrade (1.5 km gravel) | B16: 18000 | C16: F05 road conditions
A17: Insurance first-year premium | B17: 6500 | C17: SX03 + IR01
... A19: Opening inventory (F&B, soft goods) | B19: 24000 | C19: HOUSING_PARK_CONCEPT §4
A20: Subtotal | B20: 1409100
A21: Contingency 10% | B21: 140910
A22: TOTAL PHASE 1 (recommended options) | B22: 1550010 | C22: vs FINANCIAL_MODEL.md €5.5M baseline (their model assumes 30 cabins, not 5)
A24: PHASE 2 CAPEX (5 → 10 cabins) | B24: 3000000 | C24: FINANCIAL_MODEL.md baseline
A26: PHASE 3 CAPEX (10 → 30 cabins) | B26: 5900000 | C26: FINANCIAL_MODEL.md baseline
A28: TOTAL PHASE 1+2+3 | B28: 10450010 | C28: excludes land; €16.7M per Wes master plan if all-inclusive
A29: Operational runway (2 yr) [FINANCIAL_MODEL.md] | B29: 1400000 | C29: required before revenue stabilizes
A30: GRAND TOTAL | B30: 11850010 | C30: all-in cost for 30-cabin project + 2yr operational runway

Sheet Revenue
A1: REVENUE PROJECTION — 5 years × 3 scenarios
A2: Source: FINANCIAL_MODEL.md (Wes 2026-06-30) + CAPEX_OPTIONS_2026-07-06 §B.1 (ADR €220 baseline) + inflation assumption 5%/yr
A4: NEGATIVE SCENARIO (20% occupancy)
A5: Year | B5: Cabins | C5: ADR EUR | D5: Occ | E5: Cabin Rev | F5: F&B Rev | G5: Other Rev | H5: TOTAL
A6: 1 | B6: 5 | C6: 180 | D6: 0.15 | E6: =B6*365*C6*D6 | F6: =E6*0.30 | G6: =E6*0.05 | H6: =E6+F6+G6
A7: 2 | B7: 10 | C7: 200 | D7: 0.18 | E7: =B7*365*C7*D7 | F7: =E7*0.30 | G7: =E7*0.05 | H7: =E7+F7+G7
A8: 3 | B8: 30 | C8: 220 | D8: 0.2 | E8: =B8*365*C8*D8 | F8: =E8*0.30 | G8: =E8*0.05 | H8: =E8+F8+G8
A9: 4 | B9: 30 | C9: 240 | D9: 0.22 | E9: =B9*365*C9*D9 | F9: =E9*0.30 | G9: =E9*0.05 | H9: =E9+F9+G9
A10: 5 | B10: 30 | C10: 250 | D10: 0.22 | E10: =B10*365*C10*D10 | F10: =E10*0.30 | G10: =E10*0.05 | H10: =E10+F10+G10
A12: AVERAGE SCENARIO (25% occupancy)
A13: Year | B13: Cabins | C13: ADR EUR | D13: Occ | E13: Cabin Rev | F13: F&B Rev | G13: Other Rev | H13: TOTAL
A14: 1 | B14: 5 | C14: 200 | D14: 0.2 | E14: =B14*365*C14*D14 | F14: =E14*0.33 | G14: =E14*0.08 | H14: =E14+F14+G14
A15: 2 | B15: 10 | C15: 220 | D15: 0.23 | E15: =B15*365*C15*D15 | F15: =E15*0.33 | G15: =E15*0.08 | H15: =E15+F15+G15
A16: 3 | B16: 30 | C16: 240 | D16: 0.25 | E16: =B16*365*C16*D16 | F16: =E16*0.33 | G16: =E16*0.08 | H16: =E16+F16+G16
A17: 4 | B17: 30 | C17: 260 | D17: 0.28 | E17: =B17*365*C17*D17 | F17: =E17*0.33 | G17: =E17*0.08 | H17: =E17+F17+G17
A18: 5 | B18: 30 | C18: 270 | D18: 0.28 | E18: =B18*365*C18*D18 | F18: =E18*0.33 | G18: =E18*0.08 | H18: =E18+F18+G18
A20: GOOD SCENARIO (35% occupancy)
A21: Year | B21: Cabins | C21: ADR EUR | D21: Occ | E21: Cabin Rev | F21: F&B Rev | G21: Other Rev | H21: TOTAL
A22: 1 | B22: 5 | C22: 220 | D22: 0.25 | E22: =B22*365*C22*D22 | F22: =E22*0.35 | G22: =E22*0.10 | H22: =E22+F22+G22
A23: 2 | B23: 10 | C23: 240 | D23: 0.3 | E23: =B23*365*C23*D23 | F23: =E23*0.35 | G23: =E23*0.10 | H23: =E23+F23+G23
A24: 3 | B24: 30 | C24: 260 | D24: 0.35 | E24: =B24*365*C24*D24 | F24: =E24*0.35 | G24: =E24*0.10 | H24: =E24+F24+G24
A25: 4 | B25: 30 | C25: 280 | D25: 0.4 | E25: =B25*365*C25*D25 | F25: =E25*0.35 | G25: =E25*0.10 | H25: =E25+F25+G25
A26: 5 | B26: 30 | C26: 300 | D26: 0.4 | E26: =B26*365*C26*D26 | F26: =E26*0.35 | G26: =E26*0.10 | H26: =E26+F26+G26

Sheet Staff
A1: STAFF PLAN — 5 years with PY social costs (IPS 16.5% + aguinaldo 8.33% + vacaciones 5%)
A2: Source: LEGAL_RESEARCH_PACK §E.3 + PR12 (PY labor law) + FINANCIAL_MODEL.md §5
A4: Role | B4: Count | C4: Monthly EUR | D4: Annual EUR base | E4: PY social 30% | F4: Annual EUR total
A5: Resort manager (expat-grade) | B5: 1 | C5: 3500 | D5: =B5*C5*12 | E5: =D5*0.30 | F5: =D5+E5
A6: Assistant manager | B6: 1 | C6: 1500 | D6: =B6*C6*12 | E6: =D6*0.30 | F6: =D6+E6
A7: Reception (2-shift) | B7: 3 | C7: 700 | D7: =B7*C7*12 | E7: =D7*0.30 | F7: =D7+E7
A8: Head chef | B8: 1 | C8: 1200 | D8: =B8*C8*12 | E8: =D8*0.30 | F8: =D8+E8
A9: Sous chef | B9: 2 | C9: 800 | D9: =B9*C9*12 | E9: =D9*0.30 | F9: =D9+E9
A10: Line cook | B10: 2 | C10: 650 | D10: =B10*C10*12 | E10: =D10*0.30 | F10: =D10+E10
A11: Bar/service | B11: 3 | C11: 600 | D11: =B11*C11*12 | E11: =D11*0.30 | F11: =D11+E11
A12: Housekeeping (per 3 cabins) | B12: 7 | C12: 500 | D12: =B12*C12*12 | E12: =D12*0.30 | F12: =D12+E12
A13: Maintenance | B13: 2 | C13: 700 | D13: =B13*C13*12 | E13: =D13*0.30 | F13: =D13+E13
A14: Garden / hovenier | B14: 3 | C14: 600 | D14: =B14*C14*12 | E14: =D14*0.30 | F14: =D14+E14
A15: Wellness / spa staff | B15: 2 | C15: 600 | D15: =B15*C15*12 | E15: =D15*0.30 | F15: =D15+E15
A16: Security (night) | B16: 1 | C16: 600 | D16: =B16*C16*12 | E16: =D16*0.30 | F16: =D16+E16
A17: Marketing/admin | B17: 1 | C17: 800 | D17: =B17*C17*12 | E17: =D17*0.30 | F17: =D17+E17
A18: TOTAL full 30-cabin operation | B18: =SUM(B5:B17) | D18: =SUM(D5:D17) | E18: =SUM(E5:E17) | F18: =SUM(F5:F17)
A20: YEAR 1 (5 cabins, 6 staff minimum) | B20: 6 | C20: 800 | D20: =B20*C20*12 | E20: =D20*0.30 | F20: =D20+E20
A21: YEAR 2 (10 cabins, ~12 staff) | B21: 12 | C21: 800 | D21: =B21*C21*12 | E21: =D21*0.30 | F21: =D21+E21
A22: YEAR 3+ (30 cabins, full staffing) | B22: 29 | C22: 800 | D22: =B22*C22*12 | E22: =D22*0.30 | F22: =D22+E22

Sheet OperatingCosts
A1: OPERATING COSTS — variable + fixed, by scenario
A2: Source: FINANCIAL_MODEL.md §6 + LEGAL_RESEARCH_PACK §C (utility rates) + SUPPLY_CHAIN_RECOMMENDATIONS §A.16 (F&B COGS)
A4: VARIABLE (scales with occupancy)
A5: Item | B5: % of revenue / basis | C5: Note
A6: F&B COGS | B6: 38% of F&B revenue | C6: FINANCIAL_MODEL.md §6
A7: Cleaning/linen | B7: €8/occupied-room-night | C7: FINANCIAL_MODEL.md §6
A8: OTA booking fees (Booking.com/Airbnb) | B8: 15% on platform revenue | C8: avoids margin erosion; direct first
A9: Linen replacement (Phase 1) | B9: €3,000/yr | C9: low at 5 cabins
A10: Toiletries + consumables | B10: €5/guest-night | C10: premium eco-toiletries
A11: Guest experiences (welcome baskets, firewood) | B11: €10/cabin-night | C11: eco-positioning
A13: FIXED (annual, full 30 cabins)
A14: Item | B14: Year 1 (5 cab) | C14: Year 2 (10 cab) | D14: Year 3+ (30 cab)
A15: Utilities (electric, water, internet) | B15: 18000 | C15: 30000 | D15: 55000
A16: Maintenance + repairs | B16: 25000 | C16: 45000 | D16: 110000
A17: Marketing (web, OTA, social, content) | B17: 12000 | C17: 25000 | D17: 42000
A18: Insurance (forest fire + liability + workers) | B18: 6500 | C18: 12000 | D18: 28000
A19: Fuel (vehicles, generator) | B19: 8000 | C19: 15000 | D19: 25000
A20: Reserves + contingency | B20: 8000 | C20: 18000 | D20: 30000
A21: Accounting + legal (NL+PY) | B21: 6000 | C21: 8000 | D21: 12000
A22: Software (PMS, Booking.com, OTA subscriptions) | B22: 4000 | C22: 7000 | D22: 12000
A23: Permit renewals (SENATUR, Municipalidad) | B23: 2000 | C23: 3000 | D23: 5000
A24: Insurance broker fee (WTW) | B24: 0 | C24: 2000 | D24: 4000
A25: IVA / tourist tax remittance | B25: 8000 | C25: 18000 | D25: 50000
A26: TOTAL FIXED | B26: =SUM(B15:B25) | C26: =SUM(C15:C25) | D26: =SUM(D15:D25)

Sheet PnL_5year
A1: 5-YEAR P&L — GOOD SCENARIO with 4-BV structure (IRE 10% PY + NL Box 2 24.5%)
A2: Source: Revenue + Staff + OperatingCosts sheets, with the recommended 4-BV structure per LEGAL_RESEARCH §A
A4: Item | B4: Y1 | C4: Y2 | D4: Y3 | E4: Y4 | F4: Y5
A5: Total revenue (from Revenue!H22:H26) | B5: =Revenue!B22 | C5: =Revenue!C22 | D5: =Revenue!D22 | E5: =Revenue!E22 | F5: =Revenue!F22
A6: Cabin revenue | B6: 100375 | C6: 262800 | D6: 996450 | E6: 1226400 | F6: 1314000
A7: F&B revenue (35% of cabin) | B7: =B6*0.35 | C7: =C6*0.35 | D7: =D6*0.35 | E7: =E6*0.35 | F7: =F6*0.35
A8: Other revenue (10% of cabin) | B8: =B6*0.10 | C8: =C6*0.10 | D8: =D6*0.10 | E8: =E6*0.10 | F8: =F6*0.10
A9: TOTAL REVENUE | B9: =SUM(B6:B8) | C9: =SUM(C6:C8) | D9: =SUM(D6:D8) | E9: =SUM(E6:E8) | F9: =SUM(F6:F8)
A11: COSTS
A12: Staff (incl PY social costs) | B12: 70200 | C12: 140400 | D12: 338400 | E12: 338400 | F12: 338400
A13: Variable operating (F&B COGS + OTA + linen + consumables + experiences) | B13: =B7*0.38 + B6*0.05 | C13: =C7*0.38 + C6*0.05 | D13: =D7*0.38 + D6*0.05 | E13: =E7*0.38 + E6*0.05 | F13: =F7*0.38 + F6*0.05
A14: Fixed operating (utilities + maintenance + marketing + insurance + fuel + reserves + accounting + software + permits) | B14: 72500 | C14: 183000 | D14: 373000 | E14: 373000 | F14: 373000
A15: TOTAL COSTS | B15: =SUM(B12:B14) | C15: =SUM(C12:C14) | D15: =SUM(D12:D14) | E15: =SUM(E12:E14) | F15: =SUM(F12:F14)
A17: EBIT (Operating Profit) | B17: =B9-B15 | C17: =C9-C15 | D17: =D9-D15 | E17: =E9-E15 | F17: =F9-F15
A18: D&A on capex (20yr straight-line) | B18: 275000 | C18: 540000 | D18: 835000 | E18: 835000 | F18: 835000
A19: Interest expense (on €5.5M @ 7%, declining as capex builds) | B19: 385000 | C19: 280000 | D19: 200000 | E19: 150000 | F19: 100000
A20: EBT (Earnings Before Tax) | B20: =B17-B18-B19 | C20: =C17-C18-C19 | D20: =D17-D18-D19 | E20: =E17-E18-E19 | F20: =F17-F18-F19
A22: PY IRE 10% (on EBT, only if positive) | B22: =MAX(0,B20*0.10) | C22: =MAX(0,C20*0.10) | D22: =MAX(0,D20*0.10) | E22: =MAX(0,E20*0.10) | F22: =MAX(0,F20*0.10)
A23: Net Income (after PY IRE) | B23: =B20-B22 | C23: =C20-C22 | D23: =D20-D22 | E23: =E20-E22 | F23: =F20-F22
A25: DISTRIBUTION TO WES (via BV 2 dividend)
A26: Dividend declared (assume 80% of net income) | B26: =B23*0.80 | C26: =C23*0.80 | D26: =D23*0.80 | E26: =E23*0.80 | F26: =F23*0.80
A27: PY retention (BV 3 cash buffer, 20% of NI) | B27: =B23*0.20 | C27: =C23*0.20 | D27: =D23*0.20 | E27: =E23*0.20 | F27: =F23*0.20
A28: NL Box 2 (24.5% on Wes's portion) | B28: =B26*0.245 | C28: =C26*0.245 | D28: =D26*0.245 | E28: =E26*0.245 | F28: =F26*0.245
A29: Wes's NET dividend (after NL Box 2) | B29: =B26-B28 | C29: =C26-C28 | D29: =D26-D28 | E29: =E26-E28 | F29: =F26-F28
A31: EFFECTIVE TAX (combined PY IRE + NL Box 2) | B31: =(B22+B28)/B20 | C31: =(C22+C28)/C20 | D31: =(D22+D28)/D20 | E31: =(E22+E28)/E20 | F31: =(F22+F28)/F20
A32: NET RETAINED BY WES (% of EBT) | B32: =B29/B20 | C32: =C29/C20 | D32: =D29/D20 | E32: =E29/E20 | F32: =F29/F20

Sheet TaxProjection
A1: 5-YEAR TAX PROJECTION — 3 structures side-by-side (GOOD scenario, in EUR)
A2: Source: LEGAL_RESEARCH_PACK §B. The 3 structures differ in entity formation + dividend treatment
A4: STRUCTURE 1: NO BV (Wes files IB only, all income in NL)
A5: Year | B5: NL IB Box 1 (PY-source income) | C5: Notes
A6: EBT (€) | B6: =PnL_5year!B20 | C6: =PnL_5year!C20 | D6: =PnL_5year!D20 | E6: =PnL_5year!E20 | F6: =PnL_5year!F20
A7: PY tax credit (if any, via NL-PY treaty) | B7: 0 | C7: 0 | D7: 0 | E7: 0 | F7: 0
A8: NL IB Box 1 (37-49.5% progressive) | B8: =MAX(0,B6*0.37) | C8: =MAX(0,C6*0.37) | D8: =MAX(0,D6*0.495) | E8: =MAX(0,E6*0.495) | F8: =MAX(0,F6*0.495)
A9: Wes's NET (after NL IB only) | B9: =B6-B8 | C9: =C6-C8 | D9: =D6-D8 | E9: =E6-E8 | F9: =F6-F8
A11: STRUCTURE 2: 4-BV (Land PY + NL Hold + Fase 1 PY) — RECOMMENDED
A12: Year | B12: BV 3 EBT | C12: IRE 10% | D12: BV 3 NI | E12: NL Box 2 (Wes) | F12: Wes NET
A13: Y1 | B13: =PnL_5year!B20 | C13: =PnL_5year!B22 | D13: =PnL_5year!B23 | E13: =PnL_5year!B28 | F13: =PnL_5year!B29
A14: Y2 | B14: =PnL_5year!C20 | C14: =PnL_5year!C22 | D14: =PnL_5year!C23 | E14: =PnL_5year!C28 | F14: =PnL_5year!C29
A15: Y3 | B15: =PnL_5year!D20 | C15: =PnL_5year!D22 | D15: =PnL_5year!D23 | E15: =PnL_5year!D28 | F15: =PnL_5year!D29
A16: Y4 | B16: =PnL_5year!E20 | C16: =PnL_5year!E22 | D16: =PnL_5year!E23 | E16: =PnL_5year!E28 | F16: =PnL_5year!E29
A17: Y5 | B17: =PnL_5year!F20 | C17: =PnL_5year!F22 | D17: =PnL_5year!F23 | E17: =PnL_5year!F28 | F17: =PnL_5year!F29
A19: STRUCTURE 3: 5-BV (adds a 5th holding BV for Box 2 optimization)
A20: Year | B20: BV 3 EBT | C20: IRE 10% | D20: BV 3 NI | E20: NL Box 2 (Wes) | F20: Wes NET
A21: Same as Structure 2, but with participation exemption benefit
A22: Y1 | B22: =B13 | C22: =C13 | D22: =D13 | E22: =E13*0.95 | F22: =D22*0.80*0.95
A23: Y2 | B23: =B14 | C23: =C14 | D23: =D14 | E23: =E14*0.95 | F23: =D23*0.80*0.95
A24: Y3 | B24: =B15 | C24: =C15 | D24: =D15 | E24: =E15*0.95 | F24: =D24*0.80*0.95
A25: Y4 | B25: =B16 | C25: =C16 | D25: =D16 | E25: =E16*0.95 | F25: =D25*0.80*0.95
A26: Y5 | B26: =B17 | C26: =C17 | D26: =D17 | E26: =E17*0.95 | F26: =D26*0.80*0.95
A28: 5-YEAR CUMULATIVE WES NET (GOOD SCENARIO) | B28: IB only (Structure 1) | C28: 4-BV (Structure 2) | D28: 5-BV (Structure 3)
A29: 5-yr Wes NET | B29: =SUM(B9,C9,D9,E9,F9) | C29: =SUM(F13:F17) | D29: =SUM(F22:F26)
A30: 5-yr EFFECTIVE TAX (vs no-tax scenario) | B30: =B6-SUM(B9,C9,D9,E9,F9) | C30: =SUM(B6:F6)-SUM(F13:F17) | D30: =SUM(B6:F6)-SUM(F22:F26)
A31: EFFECTIVE TAX RATE (5-yr cumulative) | B31: =B30/SUM(B6:F6) | C31: =C30/SUM(B6:F6) | D31: =D30/SUM(B6:F6)
A33: BREAK-EVEN: When does the 4-BV structure beat IB-only?
A34: 4-BV saves vs IB: BV has admin cost (~€4-5K/yr) but Box 2 = 24.5% vs IB Box 1 = 37-49.5%
A35: Break-even: when net income > ~€25K/yr (4-BV pays for itself on the 12.5% Box 2 saving)
A36: Per LEGAL_RESEARCH_PACK §A.3: 4-BV is borderline advantageous in Phase 1; becomes clearly advantageous in Phase 2+

Sheet Sensitivity
A1: SENSITIVITY ANALYSIS — ADR × Occupancy matrix (Phase 1, 5 cabins)
A2: Each cell = annual cabin revenue (5 cabins × 365 × ADR × occupancy)
A4: ADR (EUR/night) ↓ / Occupancy → | B4: 0.1 | C4: 0.15 | D4: 0.2 | E4: 0.25 | F4: 0.3 | G4: 0.35 | H4: 0.4 | I4: 0.45 | J4: 0.5
A5: 150 | B5: 27375 | C5: 41062.5 | D5: 54750 | E5: 68437.5 | F5: 82125 | G5: 95812.5 | H5: 109500 | I5: 123187.5 | J5: 136875
A6: 180 | B6: 32850 | C6: 49275 | D6: 65700 | E6: 82125 | F6: 98550 | G6: 114975 | H6: 131400 | I6: 147825 | J6: 164250
A7: 200 | B7: 36500 | C7: 54750 | D7: 73000 | E7: 91250 | F7: 109500 | G7: 127750 | H7: 146000 | I7: 164250 | J7: 182500
A8: 220 | B8: 40150 | C8: 60225 | D8: 80300 | E8: 100375 | F8: 120450 | G8: 140525 | H8: 160600 | I8: 180675 | J8: 200750
A9: 240 | B9: 43800 | C9: 65700 | D9: 87600 | E9: 109500 | F9: 131400 | G9: 153300 | H9: 175200 | I9: 197100 | J9: 219000
A10: 260 | B10: 47450 | C10: 71175 | D10: 94900 | E10: 118625 | F10: 142350 | G10: 166075 | H10: 189800 | I10: 213525 | J10: 237250
A11: 280 | B11: 51100 | C11: 76650 | D11: 102200 | E11: 127750 | F11: 153300 | G11: 178850 | H11: 204400 | I11: 229950 | J11: 255500
A12: 300 | B12: 54750 | C12: 82125 | D12: 109500 | E12: 136875 | F12: 164250 | G12: 191625 | H12: 219000 | I12: 246375 | J12: 273750
A13: 350 | B13: 63875 | C13: 95812.5 | D13: 127750 | E13: 159687.5 | F13: 191625 | G13: 223562.5 | H13: 255500 | I13: 287437.5 | J13: 319375
A14: 400 | B14: 73000 | C14: 109500 | D14: 146000 | E14: 182500 | F14: 219000 | G14: 255500 | H14: 292000 | I14: 328500 | J14: 365000
A15: 500 | B15: 91250 | C15: 136875 | D15: 182500 | E15: 228125 | F15: 273750 | G15: 319375 | H15: 365000 | I15: 410625 | J15: 456250
A17: OPERATING MARGIN (REVENUE - COST) / REVENUE at 5 cabins (35% occ baseline) | B17: F&B COGS 38%, fixed ops ~€73K, staff ~€70K
A18: Below 15% occupancy = cash burn even at €300 ADR
A19: Above 25% occupancy at €200+ ADR = cash positive before debt service

Sheet Sources
A1: SOURCES — every data point in this model traces to a research file
A3: Source file | B3: Used in sheet(s) | C3: Specific data points
A4: docs/_reconciled/business/FINANCIAL_MODEL.md | B4: All | C4: €5,503,736 Phase 1 baseline, 3 occupancy scenarios, 27-staff plan, €9000/yr avg salary
A5: docs/research/RESULTS/LEGAL_RESEARCH_PACK_2026-07-06.md | B5: Assumptions + TaxProjection + P&L | C5: PY IRE 10%, NL Box 2 24.5%, IVA 5%/10%, IPS 16.5%, aguinaldo 8.33%, NL-PY treaty WHT 10% with treaty, BV > IB €70K threshold
A6: docs/research/RESULTS/CAPEX_OPTIONS_2026-07-06.md | B6: Capex + Dashboard | C6: Phase 1 €1.55M recommended, cob cabin €54K, septic €28K, solar €52.8K, quebrada+well €17K, restaurant €68K, hidden capex €115K
A7: docs/research/RESULTS/SUPPLY_CHAIN_RECOMMENDATIONS_2026-07-06.md | B7: Capex + OperatingCosts | C7: INC cement Gs. 480-580/kg, eucalyptus $45-60/m³, Gastro-Haus $28K, Sherwin-Williams $14/L, Sapucai sandstone Gs. 45K/m³, F&B COGS 38%
A8: docs/research/RESULTS/2026-06-30_construction_prices_paraguay_nl.md | B8: Capex | C8: PY construction price book (149 lines)
A9: docs/research/RESULTS/M04_cement_rebar_pricing.md | B9: Capex + OperatingCosts | C9: Cement CVE-40 Gs. 480-580/kg, rebar $720/ton, R48 time series
A10: docs/research/RESULTS/M08_septic_reed_bed.md | B10: Capex + OperatingCosts | C10: Septic + reed-bed $4,500-6,500/cabin, INAA permit
A11: docs/research/RESULTS/M_WOOD_01_structureel_hout.md | B11: Capex | C11: Eucalyptus Itapúa $45-60/m³, 4-species matrix
A12: docs/research/RESULTS/M_COB_01_cob_earthen_materialen.md | B12: Capex | C12: Cob cabin €18,200, 4 PY cob builders named
A13: docs/research/RESULTS/M22_kitchen_equipment_import.md | B13: Capex + OperatingCosts | C13: Gastro-Haus + Brasitermo, PY-dom vs BR-import
A14: docs/research/RESULTS/F09_solar_pv.md | B14: Capex + OperatingCosts | C14: Solar 8kW/cabin, $4,500/cabin PV
... A23: docs/research/RESULTS/ARCHAEOLOGICAL_CULTURAL_RESEARCH_2026-07-06.md | B23: Capex (cultural heritage section) | C23: Cultural context, Mbyá consultation cost $300-500
A26: CURRENCY CONVERSION (all EUR-base)
A27: FX rates as of 2026-07-06:
A28: 1 EUR = 1.07 USD = 8,025 PYG (BCP referencial)
A29: 1 USD = 7,500 PYG
A30: Gs. 1,000,000 = $133 = €124
A31: Inflation: EUR 2%/yr, USD 2.5%/yr, PYG 4%/yr (PY historical)
A33: OPEN ITEMS / WHAT BLOCKS FINAL NUMBERS
A34: 1. R35 drone LiDAR (€1,500) — foundation decisions need this
A35: 2. R01 site visit (HG-4) — quebrada water yield + R35 coverage
A36: 3. R07 cob builder actual quotes — 3 builders × 1 afternoon of phone calls
A37: 4. HG-1 attorney call — confirms 4-BV vs IB tax structure
A38: 5. HG-3 insurance broker quote (WTW) — locks in $22-37K/yr estimate
... A40: 7. SG-W8 year-1 revenue target from Wes — anchors the 25% occupancy baseline
